rpapack.py
setup.py
rpapack.egg-info/PKG-INFO
rpapack.egg-info/SOURCES.txt
rpapack.egg-info/dependency_links.txt
rpapack.egg-info/top_level.txt