Metadata-Version: 1.0
Name: rpapack
Version: 2.2.2
Summary: use to create rpa extension
Home-page: UNKNOWN
Author: sanco
Author-email: sanco1987@gmail.com
License: UNKNOWN
Keywords: rpa
Platform: UNKNOWN
